scrape_highlighted.py
setup.py
scrape_highlighted.egg-info/PKG-INFO
scrape_highlighted.egg-info/SOURCES.txt
scrape_highlighted.egg-info/dependency_links.txt
scrape_highlighted.egg-info/requires.txt
scrape_highlighted.egg-info/top_level.txt