Metadata-Version: 1.0
Name: scrape-highlighted
Version: 0.2.1
Summary: A script to scrape highlighted text from a pdf [Mac only].
Home-page: http://bitbucket.org/lars512/scrape-highlighted/
Author: Lars Yencken
Author-email: lljy@csse.unimelb.edu.au
License: BSD
Platform: UNKNOWN
